[{
    "_id": "5d713995b721c3bb38c1f5d0",
    "title": "Mężczyźni, którzy nienawidzą kobiet",
    "author": "Stieg Larsson",
    "publisher": "Czarna Owca",
    "category": "5deff118c426854752e9b62d"
  },
  {
    "_id": "5d713a66ec8f2b88b8f830b8",
    "title": "Harry Potter i Kamień Filozoficzny",
    "author": "J.K. Rowling",
    "publisher": "Media Rodzina",
    "category": "5deff118c426854752e9b64d"
  },
  {
    "_id": "5d725a037b292f5f8ceff787",
    "title": "Harry Potter i Komnata Tajemnic",
    "author": "J.K. Rowling",
    "publisher": "Media Rodzina",
    "category": "5deff118c426854752e9b64d"
  },
  {
    "_id": "5d725a1b7b292f5f8ceff788",
    "title": "Władca pierścieni",
    "author": "J.R.R. Tolkien",
    "publisher": "Amber",
    "category": "5deff118c426854752e9b61d"
  }
]